odoo10_addon_pos_lot_selection-10.0.1.0.0-py2.7-nspkg.pth
odoo/addons/pos_lot_selection/README.rst
odoo/addons/pos_lot_selection/__init__.py
odoo/addons/pos_lot_selection/__manifest__.py
odoo/addons/pos_lot_selection/i18n/es.po
odoo/addons/pos_lot_selection/static/description/icon.png
odoo/addons/pos_lot_selection/static/src/css/pos.css
odoo/addons/pos_lot_selection/static/src/js/chrome.js
odoo/addons/pos_lot_selection/static/src/js/models.js
odoo/addons/pos_lot_selection/static/src/xml/pos.xml
odoo/addons/pos_lot_selection/templates/assets.xml
odoo10_addon_pos_lot_selection-10.0.1.0.0.dist-info/DESCRIPTION.rst
odoo10_addon_pos_lot_selection-10.0.1.0.0.dist-info/METADATA
odoo10_addon_pos_lot_selection-10.0.1.0.0.dist-info/RECORD
odoo10_addon_pos_lot_selection-10.0.1.0.0.dist-info/WHEEL
odoo10_addon_pos_lot_selection-10.0.1.0.0.dist-info/metadata.json
odoo10_addon_pos_lot_selection-10.0.1.0.0.dist-info/namespace_packages.txt
odoo10_addon_pos_lot_selection-10.0.1.0.0.dist-info/top_level.txt
